example/source/conf.py
sphinx_redirect_by_id/__init__.py
sphinx_redirect_by_id/redirect.html_t
sphinx_redirect_by_id/redirecttools.js
sphinx_redirect_by_id-0.1.3.dist-info/LICENSE
sphinx_redirect_by_id-0.1.3.dist-info/METADATA
sphinx_redirect_by_id-0.1.3.dist-info/WHEEL
sphinx_redirect_by_id-0.1.3.dist-info/top_level.txt
sphinx_redirect_by_id-0.1.3.dist-info/RECORD
