Metadata-Version: 2.1
Name: sphinx-redirect-by-id
Version: 0.1.3
Summary: A Sphinx extension to provide redirection to an entity by its ID.
Author-email: Jakob Lykke Andersen <Jakob@caput.dk>
License: License for Sphinx
Project-URL: Homepage, https://github.com/jakobandersen/sphinx-redirect-by-id
Project-URL: Bug Tracker, https://github.com/jakobandersen/sphinx-redirect-by-id/issues
Classifier: Programming Language :: Python :: 3
Classifier: License :: OSI Approved :: BSD License
Classifier: Operating System :: OS Independent
Classifier: Framework :: Sphinx :: Extension
Requires-Python: >=3.7
License-File: LICENSE
Requires-Dist: sphinx (>=5.0)
